pyIslam/__init__.py
pyIslam/baselib.py
pyIslam/hijri.py
pyIslam/mirath.py
pyIslam/praytimes.py
pyIslam/qiblah.py
pyIslam/ummalqura.py
pyIslam/ummalqura_table.py
pyIslam/zakat.py
islam-2.2.0.dist-info/LICENSE.md
islam-2.2.0.dist-info/METADATA
islam-2.2.0.dist-info/WHEEL
islam-2.2.0.dist-info/top_level.txt
islam-2.2.0.dist-info/RECORD
