Metadata-Version: 2.1
Name: islam
Version: 2.2.0
Summary: a library to calculate prayer times, hijri date, qiblah direction and more
Home-page: https://github.com/abougouffa/pyIslam
Author: abougouffa
Author-email: abougouffa@fedoraproject.org
License: GPL3+
Keywords: prayer times,hijri date,qiblah direction
Platform: UNKNOWN
Classifier: Intended Audience :: Developers
Classifier: Topic :: Utilities
Classifier: License :: OSI Approved :: GNU Lesser General Public License v3 or later (LGPLv3+)
Classifier: Natural Language :: English
Classifier: Operating System :: OS Independent
Classifier: Programming Language :: Python
Classifier: Programming Language :: Python :: 3.7
License-File: LICENSE.md
